LICENSE.md
MANIFEST.in
README.md
setup.cfg
setup.py
ii_django_package_settings/__init__.py
ii_django_package_settings/settings.py
ii_django_package_settings.egg-info/PKG-INFO
ii_django_package_settings.egg-info/SOURCES.txt
ii_django_package_settings.egg-info/dependency_links.txt
ii_django_package_settings.egg-info/not-zip-safe
ii_django_package_settings.egg-info/top_level.txt