Metadata-Version: 1.1
Name: ii-django-package-settings
Version: 0.1
Summary: ideallical django package settings
Home-page: https://github.com/ideallical/ii-django-package-settings
Author: ideallical
Author-email: info@ideallical.com
License: BSD
Download-URL: https://github.com/ideallical/ii-django-package-settings/archive/0.1.tar.gz
Keywords: django,package,settings
Platform: UNKNOWN
